{
    "songs": [
        {
            "date": "d",
            "artist": "d",
            "name": "d",
            "info": "d"
        },
        {
            "date": "l",
            "artist": "l",
            "name": "l",
            "info": "l"
        },
        {
            "date": "o",
            "artist": "o",
            "name": "o",
            "info": "o"
        },
        {
            "date": "g",
            "artist": "g",
            "name": "g",
            "info": "g"
        },
        {
            "date": "t",
            "artist": "t",
            "name": "t",
            "info": "t"
        },
        {
            "date": "f",
            "artist": "f",
            "name": "f",
            "info": "f"
        },
        {
            "date": "p",
            "artist": "p",
            "name": "p",
            "info": "p"
        }
    ],
    "name": "hi"
}